drexml-1.1.3.dist-info/METADATA
drexml-1.1.3.dist-info/WHEEL
drexml-1.1.3.dist-info/entry_points.txt
drexml-1.1.3.dist-info/licenses/LICENSE.txt
drexml/__init__.py
drexml/cli/__init__.py
drexml/cli/cli.py
drexml/cli/stab_explainer.py
drexml/cli/stab_scorer.py
drexml/cli/stab_trainer.py
drexml/config.py
drexml/datasets.py
drexml/explain.py
drexml/models.py
drexml/plotting.py
drexml/postprocess.py
drexml/pystab.py
drexml/resources/__init__.py
drexml/resources/circuit_names.tsv.gz
drexml/resources/circuits1.tsv.gz
drexml/resources/circuits2genes_gtex-v8_hipathia-v2-14-0.tsv.gz
drexml/resources/curated_gene_disease_associations.tsv.gz
drexml/resources/genes_drugbank-v050110_gtex-v8_mygene-v20230220.tsv.gz
drexml/utils.py
drexml-1.1.3.dist-info/RECORD
