Metadata-Version: 2.1
Name: drexml
Version: 1.1.3
Summary: (DRExM³L) Drug REpurposing using and eXplainable Machine Learning and Mechanistic Models of signal transduction"
Author-Email: Carlos Loucera <carlos.loucera@juntadeandalucia.es>, Marina Esteban-Medina <marina.esteban@juntadeandalucia.es>, Maria Pena-Chilet <maria.pena.chilet.ext@juntadeandalucia.es.com>, =?utf-8?q?V=C3=ADctor_Manuel_de_la_Oliva_Roque?= <victorm.oliva@juntadeandalucia.es>, =?utf-8?q?Sara_Herr=C3=A1iz-Gil_?= <sherraiz@ing.uc3m.es>
License: MIT
Requires-Python: <3.11,>=3.8
Requires-Dist: scikit-learn>=1.3.0
Requires-Dist: numpy<2.0,>=1.24.4
Requires-Dist: scipy>=1.10.1
Requires-Dist: pandas>=2.0.3
Requires-Dist: seaborn>=0.12.2
Requires-Dist: shap==0.42.0
Requires-Dist: matplotlib>=3.7.2
Requires-Dist: python-dotenv>=1.0.0
Requires-Dist: pyarrow>=12.0.1
Requires-Dist: statsmodels>=0.14.0
Requires-Dist: pystow>=0.5.0
